Metadata-Version: 2.1
Name: rdme-cli
Version: 0.0.4
Summary: Redme.io cli
Home-page: https://github.com/creditas/rdme-cli
Author: Aurelio Saraiva
Author-email: aurelio.saraiva@creditas.com.br
License: UNKNOWN
Platform: UNKNOWN
Classifier: Programming Language :: Python :: 3
Classifier: License :: OSI Approved :: MIT License
Classifier: Operating System :: OS Independent
